LICENSE
MANIFEST.in
README.rst
setup.py
pyreactive/__init__.py
pyreactive/mutables.py
pyreactive/postfix.py
pyreactive/pyreactive.py
pyreactive.egg-info/PKG-INFO
pyreactive.egg-info/SOURCES.txt
pyreactive.egg-info/dependency_links.txt
pyreactive.egg-info/top_level.txt